LICENSE
MANIFEST.in
README.md
requirements.txt
setup.py
sapguipy/__init__.py
sapguipy/sap.py
sapguipy.egg-info/PKG-INFO
sapguipy.egg-info/SOURCES.txt
sapguipy.egg-info/dependency_links.txt
sapguipy.egg-info/requires.txt
sapguipy.egg-info/top_level.txt