Metadata-Version: 2.1
Name: sapguipy
Version: 0.0.6
Summary: Manipulate SAP GUI with some lines of code
Author: Nicolas Passos
Author-email: nicolasduart21@gmail.com
License: MIT License
Keywords: sap
Requires-Python: >=3.8
License-File: LICENSE
